maruadmin_agent/VERSION
maruadmin_agent/__init__.py
maruadmin_agent/certificate_manager.py
maruadmin_agent/cli.py
maruadmin_agent/command_handler.py
maruadmin_agent/config.py
maruadmin_agent/docker_manager.py
maruadmin_agent/haproxy_manager.py
maruadmin_agent/main.py
maruadmin_agent/metrics_collector.py
maruadmin_agent/metrics_transmitter.py
maruadmin_agent/monitor.py
maruadmin_agent/ssh_server.py
maruadmin_agent/utils.py
maruadmin_agent-0.3.5.dist-info/METADATA
maruadmin_agent-0.3.5.dist-info/WHEEL
maruadmin_agent-0.3.5.dist-info/entry_points.txt
maruadmin_agent-0.3.5.dist-info/top_level.txt
maruadmin_agent-0.3.5.dist-info/RECORD
