Metadata-Version: 2.4
Name: maruadmin-agent
Version: 0.3.5
Summary: MaruAdmin Remote Server Management Agent
Author: MaruAdmin Team
License: MIT
Project-URL: Homepage, https://github.com/dirmich/maruadmin
Project-URL: Repository, https://github.com/dirmich/maruadmin
Project-URL: Issues, https://github.com/dirmich/maruadmin/issues
Keywords: server,management,monitoring,agent,docker,haproxy
Classifier: Development Status :: 3 - Alpha
Classifier: Intended Audience :: System Administrators
Classifier: Programming Language :: Python :: 3
Classifier: Programming Language :: Python :: 3.8
Classifier: Programming Language :: Python :: 3.9
Classifier: Programming Language :: Python :: 3.10
Classifier: Programming Language :: Python :: 3.11
Classifier: Programming Language :: Python :: 3.12
Classifier: License :: OSI Approved :: MIT License
Classifier: Operating System :: POSIX :: Linux
Classifier: Operating System :: MacOS
Classifier: Topic :: System :: Monitoring
Classifier: Topic :: System :: Systems Administration
Requires-Python: >=3.8
Requires-Dist: paramiko>=3.0.0
Requires-Dist: psutil>=5.9.0
Requires-Dist: requests>=2.28.0
Requires-Dist: cryptography>=40.0.0
Dynamic: requires-python
